LICENSE
MANIFEST.in
README.md
requirements.txt
setup.py
docs/source/conf.py
torchcs/__init__.py
torchcs/version.py
torchcs.egg-info/PKG-INFO
torchcs.egg-info/SOURCES.txt
torchcs.egg-info/dependency_links.txt
torchcs.egg-info/requires.txt
torchcs.egg-info/top_level.txt
torchcs/dictionary/__init__.py
torchcs/dictionary/dcts.c
torchcs/dictionary/dcts.pyi
torchcs/dictionary/dfts.c
torchcs/dictionary/dfts.pyi
torchcs/dictionary/dictshow.c
torchcs/dictionary/dictshow.pyi
torchcs/dictionary/dwts.c
torchcs/dictionary/dwts.pyi
torchcs/dictionary/mldict.c
torchcs/dictionary/mldict.pyi
torchcs/dictionary/swap.c
torchcs/dictionary/swap.pyi
torchcs/recovery/__init__.py
torchcs/recovery/approximate_message_passing.c
torchcs/recovery/approximate_message_passing.pyi
torchcs/recovery/csnet1d.c
torchcs/recovery/csnet1d.pyi
torchcs/recovery/fistanet1d.c
torchcs/recovery/fistanet1d.pyi
torchcs/recovery/ista_fista.c
torchcs/recovery/ista_fista.pyi
torchcs/recovery/iterative_adaptive_approch.c
torchcs/recovery/iterative_adaptive_approch.pyi
torchcs/recovery/matching_pursuit.c
torchcs/recovery/matching_pursuit.pyi
torchcs/recovery/srnet1d.c
torchcs/recovery/srnet1d.pyi
torchcs/sensing/__init__.py
torchcs/sensing/bernoullis.c
torchcs/sensing/bernoullis.pyi
torchcs/sensing/binary.c
torchcs/sensing/binary.pyi
torchcs/sensing/gaussians.c
torchcs/sensing/gaussians.pyi
torchcs/sensing/toeplitz.c
torchcs/sensing/toeplitz.pyi
torchcs/sharing/__init__.py
torchcs/sharing/nonlinearfn.c
torchcs/sharing/nonlinearfn.pyi
torchcs/sharing/normalization.c
torchcs/sharing/normalization.pyi
torchcs/signal/__init__.py
torchcs/signal/pulses.c
torchcs/signal/pulses.pyi
torchcs/signal/sincos.c
torchcs/signal/sincos.pyi